{
  "DbscenariosExecuteSV_ByteDatetime" : {
    "_id" : "wm-DbscenariosExecuteSV_ByteDatetime-wm.ServiceVariable-1488952655357",
    "name" : "DbscenariosExecuteSV_ByteDatetime",
    "owner" : "Page",
    "category" : "wm.ServiceVariable",
    "dataBinding" : [ ],
    "type" : "com.testingallprocedurescenarios.dbscenarios.models.query.SvByteDatetimeResponse",
    "service" : "dbscenarios",
    "operation" : "executeSV_ByteDatetime",
    "operationId" : "QueryExecutionController_executeSV_ByteDatetime",
    "operationType" : "get",
    "serviceType" : "DataService",
    "dataSet" : [ ],
    "isList" : true,
    "maxResults" : 20,
    "designMaxResults" : 10,
    "startUpdate" : true,
    "autoUpdate" : true,
    "inFlightBehavior" : "executeLast",
    "transformationRequired" : false,
    "saveInPhonegap" : false,
    "isDefault" : true,
    "controller" : "QueryExecution"
  },
  "serviceVariable1" : {
    "_id" : "wm-serviceVariable1-wm.ServiceVariable-1488967363763",
    "name" : "serviceVariable1",
    "owner" : "Page",
    "category" : "wm.ServiceVariable",
    "dataBinding" : [ ],
    "type" : "com.testingallprocedurescenarios.dbscenarios.models.query.SvLoggedinUserResponse",
    "service" : "dbscenarios",
    "operation" : "executeSV_LoggedinUser",
    "operationId" : "QueryExecutionController_executeSV_LoggedinUser",
    "operationType" : "get",
    "serviceType" : "DataService",
    "dataSet" : [ ],
    "isList" : true,
    "maxResults" : 2,
    "designMaxResults" : 10,
    "startUpdate" : true,
    "autoUpdate" : true,
    "inFlightBehavior" : "executeLast",
    "transformationRequired" : false,
    "saveInPhonegap" : false,
    "controller" : "QueryExecution"
  }
}